[
  {
    "id": "move.spectralize",
    "title": "Spectralize",
    "description": "Reinterpret zeros, gaps, stability or obstructions as eigenvalues, spectra or trace data.",
    "good_for": [
      "problem.riemann_hypothesis",
      "problem.yang_mills_mass_gap",
      "domain.pde"
    ],
    "output": "candidate operator, spectral gap statement or trace identity",
    "risks": [
      "The operator may not be self-adjoint.",
      "Spectral data may be only analogy."
    ],
    "lean_test": "Create a finite-dimensional matrix model and prove the toy spectral statement."
  },
  {
    "id": "move.categorify",
    "title": "Categorify",
    "description": "Replace sets or equations by objects, morphisms, functors and natural transformations.",
    "good_for": [
      "domain.algebraic_geometry",
      "problem.hodge_conjecture",
      "problem.p_vs_np"
    ],
    "output": "functorial dictionary or universal property",
    "risks": [
      "The categorical lift may hide the original hard estimate."
    ],
    "lean_test": "State the relevant universal property in a small category."
  },
  {
    "id": "move.geometrize",
    "title": "Geometrize",
    "description": "Translate algebraic, analytic or computational data into geometric objects and invariants.",
    "good_for": [
      "problem.p_vs_np",
      "problem.hodge_conjecture",
      "problem.birch_swinnerton_dyer"
    ],
    "output": "variety, moduli space, bundle, curvature or geometric invariant",
    "risks": [
      "The geometry may not preserve the invariant needed for the problem."
    ],
    "lean_test": "Formalize the toy geometric object and one preserved invariant."
  },
  {
    "id": "move.probabilize",
    "title": "Probabilize",
    "description": "Use random models, typical cases, concentration or stochastic dynamics to expose structure.",
    "good_for": [
      "problem.navier_stokes",
      "problem.p_vs_np",
      "problem.riemann_hypothesis"
    ],
    "output": "random model, concentration claim or stochastic analogue",
    "risks": [
      "Average behavior may erase worst-case or singular behavior."
    ],
    "lean_test": "Build a finite probability model with explicit event bounds."
  },
  {
    "id": "move.renormalize",
    "title": "Renormalize",
    "description": "Track how quantities change across scales and search for fixed points or monotonicity.",
    "good_for": [
      "problem.navier_stokes",
      "problem.yang_mills_mass_gap",
      "domain.quantum_field_theory"
    ],
    "output": "scale flow, critical exponent, invariant or monotone quantity",
    "risks": [
      "The flow may be heuristic without a rigorous topology."
    ],
    "lean_test": "Prove a finite scale-recursion lemma."
  },
  {
    "id": "move.dualize",
    "title": "Dualize",
    "description": "Reverse perspective using dual spaces, Pontryagin/Fourier duality, categorical duals or primal-dual optimization.",
    "good_for": [
      "domain.harmonic_analysis",
      "domain.functional_analysis",
      "domain.category_theory"
    ],
    "output": "dual problem or transformed obstruction",
    "risks": [
      "The dual problem can lose positivity, locality or computability."
    ],
    "lean_test": "State the dual construction and prove involutivity in a toy case."
  },
  {
    "id": "move.local_to_global",
    "title": "Local to global",
    "description": "Patch local data into global structure or identify the obstruction to gluing.",
    "good_for": [
      "domain.topology",
      "domain.algebraic_geometry",
      "problem.navier_stokes"
    ],
    "output": "sheaf, descent condition, compactness argument or obstruction class",
    "risks": [
      "Local solvability may not control global compatibility."
    ],
    "lean_test": "Formalize a tiny gluing lemma or counterexample."
  },
  {
    "id": "move.deform",
    "title": "Deform",
    "description": "Study a family instead of a single object, then analyze limits, degenerations or stability.",
    "good_for": [
      "problem.birch_swinnerton_dyer",
      "problem.hodge_conjecture",
      "domain.pde"
    ],
    "output": "family, parameter space, degeneration or stability invariant",
    "risks": [
      "The special fiber may not preserve the desired property."
    ],
    "lean_test": "Represent a finite family and prove a property is stable under a simple deformation."
  },
  {
    "id": "move.tropicalize",
    "title": "Tropicalize",
    "description": "Pass to piecewise-linear or valuation shadows to expose combinatorial structure.",
    "good_for": [
      "domain.algebraic_geometry",
      "domain.number_theory",
      "problem.p_vs_np"
    ],
    "output": "polyhedral or valuation model",
    "risks": [
      "The shadow may be too coarse to recover the original invariant."
    ],
    "lean_test": "Formalize a valuation-like toy map and preserved inequality."
  },
  {
    "id": "move.finitize",
    "title": "Finitize",
    "description": "Replace a continuous or infinite object by a finite toy model that preserves one mechanism.",
    "good_for": [
      "problem.yang_mills_mass_gap",
      "problem.navier_stokes",
      "problem.riemann_hypothesis"
    ],
    "output": "finite model, computable experiment or small Lean theorem",
    "risks": [
      "Finite artifacts can create false structure."
    ],
    "lean_test": "Prove the finite toy theorem completely."
  },
  {
    "id": "move.find_barrier",
    "title": "Find the barrier",
    "description": "Identify why standard methods fail and encode the failure as an invariant or obstruction.",
    "good_for": [
      "problem.p_vs_np",
      "problem.navier_stokes",
      "problem.riemann_hypothesis",
      "bridge.target_erasure_diagnostic"
    ],
    "output": "barrier statement, obstruction invariant or no-go lemma",
    "risks": [
      "The named barrier may be sociological rather than mathematical."
    ],
    "lean_test": "Formalize the simplest version of the obstruction."
  },
  {
    "id": "move.transfer_by_functor",
    "title": "Transfer by functor",
    "description": "Move a problem through a functor or equivalence while tracking which structure is preserved.",
    "good_for": [
      "domain.category_theory",
      "domain.representation_theory",
      "domain.algebraic_geometry"
    ],
    "output": "source category, target category, preserved structure and lost structure",
    "risks": [
      "The functor may forget exactly the hard information."
    ],
    "lean_test": "Define a small functor and prove preservation of one property."
  },
  {
    "id": "move.cancel_before_majorizing",
    "title": "Cancel before majorizing",
    "description": "Preserve signed, graded or symmetry-related contributions long enough to apply an exact or defective Ward identity before taking norms and triangle inequalities.",
    "good_for": [
      "bridge.ward_defect_weight_variation",
      "bridge.cluster_expansion_with_holes",
      "problem.uniform_yang_mills_rg_activity"
    ],
    "output": "a decomposition into an exact sector, a quantified defect and a residual activity profile",
    "risks": [
      "An abstract differential may not act on the actual measure or regulator.",
      "Taking absolute values too early destroys the cancellation being tested."
    ],
    "lean_test": "Prove the finite weighted Ward identity and derive a norm bound controlled only by the weight variation."
  },
  {
    "id": "move.separate_support_roles",
    "title": "Separate support roles",
    "description": "Use distinct support maps for connectivity or incompatibility and for full target union or locality, then prove the comparison theorem explicitly.",
    "good_for": [
      "bridge.cluster_expansion_with_holes",
      "domain.renormalization_group",
      "problem.uniform_yang_mills_rg_activity"
    ],
    "output": "two support maps, an active-target comparison and a target-fiber identity without lost multiplicity",
    "risks": [
      "Collapsing the supports can create false factorization or erase multiple connected covers with the same target."
    ],
    "lean_test": "Prove target-map injectivity only inside admissible families and retain a fiber sum for duplicate targets."
  },
  {
    "id": "move.rescale_physical_units",
    "title": "Rescale physical units",
    "description": "Separate dimensionless lattice quantities from physical units and track exact invariants before taking continuum or thermodynamic limits.",
    "good_for": [
      "bridge.lattice_physical_scaling",
      "domain.renormalization_group",
      "problem.yang_mills_mass_gap"
    ],
    "output": "an exact unit-conversion identity plus explicit convergence and finite-volume obligations",
    "risks": [
      "An arbitrarily chosen lattice spacing can manufacture a meaningless physical scale.",
      "A decay-rate witness need not equal the optimal spectral mass."
    ],
    "lean_test": "Prove the exponent identity, ceiling approximation error and block-scale invariance of the physical mass ratio."
  },
  {
    "id": "move.preserve_exact_target",
    "title": "Preserve the exact target",
    "description": "Delay global overcounting until the exact union fiber, target label and local relation have produced every conclusion that depends on them.",
    "good_for": [
      "bridge.cluster_expansion_with_holes",
      "bridge.target_preserving_ursell_summation",
      "problem.yang_mills_mass_gap"
    ],
    "output": "fixed-target summation with an extracted target weight and an explicit remaining local kernel",
    "risks": [
      "The retained state can make finite reindexing and dependent bookkeeping substantially harder."
    ],
    "lean_test": "Define a finite exact-union fiber and prove that metric extraction holds before, but need not hold after, forgetting the target."
  },
  {
    "id": "move.eliminate_tree_leaves",
    "title": "Eliminate tree leaves",
    "description": "Orient a connected tree from a root and sum assignments from the leaves upward using parent-child kernel moments and accumulated child powers.",
    "good_for": [
      "bridge.rooted_leaf_factorial_moments",
      "bridge.target_preserving_ursell_summation",
      "domain.renormalization_group"
    ],
    "output": "fixed-tree assignment bound with child-count factorials and a separately auditable tree-shape sum",
    "risks": [
      "A global child budget can reintroduce volume dependence if incompatibility with the parent is not retained."
    ],
    "lean_test": "Prove the bound for rooted trees with at most three vertices and then generalize by deleting a maximal-depth leaf."
  },
  {
    "id": "move.audit_information_loss",
    "title": "Audit information loss",
    "description": "For every abstraction or majorant, list the target, locality, signs, edges and scale data it forgets, then test whether the desired conclusion still mentions them.",
    "good_for": [
      "bridge.target_erasure_diagnostic",
      "domain.polymer_cluster_expansions",
      "bridge.ward_defect_weight_variation"
    ],
    "output": "retained-versus-forgotten data table, circularity check and smallest finite counterexample",
    "risks": [
      "Applied indiscriminately, the audit can reject coarse bounds that are valid after the relevant structure has already been consumed."
    ],
    "lean_test": "Prove an exact factorization of the coarse object and exhibit two inputs with the same coarse data but different target-sensitive statistics."
  }
]
